rong/__init__.py
rong/enums.py
rong/utils.py
rong-0.0.3.dist-info/METADATA
rong-0.0.3.dist-info/WHEEL
rong-0.0.3.dist-info/licenses/LICENSE
rong-0.0.3.dist-info/RECORD
