Metadata-Version: 2.1
Name: rong
Version: 0.0.3
Summary: A coloring utility for Python console apps.
Project-URL: Homepage, https://github.com/Almas-Ali/rong
Project-URL: Documentation, https://github.com/Almas-Ali/rong#readme
Project-URL: Repository, https://github.com/Almas-Ali/rong
Project-URL: Bug Tracker, https://github.com/Almas-Ali/rong/issues
Author-email: "Md. Almas Ali" <almaspr3@gmail.com>
Maintainer-email: "Md. Almas Ali" <almaspr3@gmail.com>
License: MIT License
License-File: LICENSE
Keywords: background,color,colored,coloring,colour,console,foreground,formatting,rgb,rong,style,terminal,text,utility
Classifier: Development Status :: 5 - Production/Stable
Classifier: Environment :: Console
Classifier: Intended Audience :: Developers
Classifier: License :: OSI Approved :: MIT License
Classifier: Natural Language :: English
Classifier: Programming Language :: Python
Classifier: Programming Language :: Python :: 3
Classifier: Programming Language :: Python :: 3 :: Only
Classifier: Programming Language :: Python :: 3.7
Classifier: Programming Language :: Python :: 3.8
Classifier: Programming Language :: Python :: 3.9
Classifier: Programming Language :: Python :: 3.10
Classifier: Programming Language :: Python :: 3.11
Classifier: Programming Language :: Python :: 3.12
Requires-Python: >=3.7
